unitfield/__init__.py
unitfield/py.typed
unitfield/core/__init__.py
unitfield/core/enums.py
unitfield/core/types.py
unitfield/core/unitfield.py
unitfield/interpolation/__init__.py
unitfield/interpolation/interp_cv2.py
unitfield/interpolation/interp_np.py
unitfield/utilities/__init__.py
unitfield/utilities/positional_basematrix.py
unitfield-0.1.3.dist-info/licenses/LICENSE
unitfield-0.1.3.dist-info/METADATA
unitfield-0.1.3.dist-info/WHEEL
unitfield-0.1.3.dist-info/top_level.txt
unitfield-0.1.3.dist-info/RECORD
